eadfv/__init__.py
eadfv/eadfv.py
eadfv-0.1.dist-info/METADATA
eadfv-0.1.dist-info/WHEEL
eadfv-0.1.dist-info/top_level.txt
eadfv-0.1.dist-info/RECORD
